{
  "nodes": [
    {
      "id": 0,
      "label": "Entry",
      "line": null
    },
    {
      "id": 1,
      "label": "Exit",
      "line": null
    },
    {
      "id": 2,
      "label": "Try",
      "line": 9
    },
    {
      "id": 3,
      "label": "If(BinaryOperation(operandl=BinaryOperation(operandl=Literal(postfix_operators=[], prefix_operators=[], qualifier=None, selectors=[], value=null), operandr=Literal(postfix_operators=[], prefix_operators=[], qualifier=None, selectors=[], value=false), operator=&), operandr=Literal(postfix_operators=[], prefix_operators=[], qualifier=None, selectors=[], value=false), operator=&&))",
      "line": 10
    },
    {
      "id": 4,
      "label": "LocalVariableDeclaration(annotations=[], declarators=[VariableDeclarator(dimensions=[], initializer=Literal(postfix_operators=[], prefix_operators=[], qualifier=None, selectors=[], value='2'), name=__cfwr_obj96)], modifiers=set(), type=BasicType(dimensions=[], name=char))",
      "line": 11
    },
    {
      "id": 5,
      "label": "Catch(__cfwr_e61)",
      "line": null
    },
    {
      "id": 6,
      "label": "Assignment(expressionl=This(postfix_operators=[], prefix_operators=[], qualifier=None, selectors=[MemberReference(member=size, postfix_operators=None, prefix_operators=None, qualifier=None, selectors=None)]), type==, value=MemberReference(member=size, postfix_operators=[], prefix_operators=[], qualifier=, selectors=[]))",
      "line": 17
    },
    {
      "id": 7,
      "label": "Assignment(expressionl=This(postfix_operators=[], prefix_operators=[], qualifier=None, selectors=[MemberReference(member=vDown, postfix_operators=None, prefix_operators=None, qualifier=None, selectors=None)]), type==, value=ArrayCreator(dimensions=[This(postfix_operators=[], prefix_operators=[], qualifier=None, selectors=[MemberReference(member=size, postfix_operators=None, prefix_operators=None, qualifier=None, selectors=None)])], initializer=None, postfix_operators=[], prefix_operators=[], qualifier=None, selectors=[], type=BasicType(dimensions=None, name=int)))",
      "line": 18
    },
    {
      "id": 8,
      "label": "Assignment(expressionl=MemberReference(member=vDown, postfix_operators=[], prefix_operators=[], qualifier=, selectors=[ArraySelector(index=BinaryOperation(operandl=Literal(postfix_operators=[], prefix_operators=[], qualifier=None, selectors=[], value=1), operandr=MemberReference(member=value, postfix_operators=[], prefix_operators=[], qualifier=, selectors=[]), operator=+))]), type==, value=Literal(postfix_operators=[], prefix_operators=[], qualifier=None, selectors=[], value=10))",
      "line": 19
    }
  ],
  "edges": [
    {
      "source": 0,
      "target": 2
    },
    {
      "source": 2,
      "target": 3
    },
    {
      "source": 2,
      "target": 5
    },
    {
      "source": 3,
      "target": 4
    },
    {
      "source": 3,
      "target": 6
    },
    {
      "source": 4,
      "target": 6
    },
    {
      "source": 5,
      "target": 6
    },
    {
      "source": 6,
      "target": 7
    },
    {
      "source": 7,
      "target": 8
    },
    {
      "source": 8,
      "target": 1
    }
  ]
}