{
  "nodes": [
    {
      "id": 0,
      "label": "Entry",
      "line": null
    },
    {
      "id": 1,
      "label": "Exit",
      "line": null
    },
    {
      "id": 2,
      "label": "Try",
      "line": 42
    },
    {
      "id": 3,
      "label": "Return(Literal(postfix_operators=[], prefix_operators=['-'], qualifier=None, selectors=[], value=56.72f))",
      "line": 32
    },
    {
      "id": 4,
      "label": "Catch(__cfwr_e93)",
      "line": null
    },
    {
      "id": 5,
      "label": "While(Literal(postfix_operators=[], prefix_operators=[], qualifier=None, selectors=[], value=true))",
      "line": 36
    },
    {
      "id": 6,
      "label": "For(BinaryOperation(operandl=MemberReference(member=__cfwr_i64, postfix_operators=[], prefix_operators=[], qualifier=, selectors=[]), operandr=Literal(postfix_operators=[], prefix_operators=[], qualifier=None, selectors=[], value=2), operator=<))",
      "line": 38
    },
    {
      "id": 7,
      "label": "For(BinaryOperation(operandl=MemberReference(member=__cfwr_i49, postfix_operators=[], prefix_operators=[], qualifier=, selectors=[]), operandr=Literal(postfix_operators=[], prefix_operators=[], qualifier=None, selectors=[], value=3), operator=<))",
      "line": 39
    },
    {
      "id": 8,
      "label": "If(BinaryOperation(operandl=BinaryOperation(operandl=BinaryOperation(operandl=Literal(postfix_operators=[], prefix_operators=[], qualifier=None, selectors=[], value=true), operandr=Literal(postfix_operators=[], prefix_operators=['-'], qualifier=None, selectors=[], value=654), operator=&), operandr=Literal(postfix_operators=[], prefix_operators=[], qualifier=None, selectors=[], value=82.28f), operator=-), operandr=BinaryOperation(operandl=Literal(postfix_operators=[], prefix_operators=[], qualifier=None, selectors=[], value=null), operandr=Literal(postfix_operators=[], prefix_operators=[], qualifier=None, selectors=[], value=null), operator=<<), operator=&&))",
      "line": 40
    },
    {
      "id": 9,
      "label": "While(BinaryOperation(operandl=Literal(postfix_operators=[], prefix_operators=['-'], qualifier=None, selectors=[], value=11), operandr=Literal(postfix_operators=[], prefix_operators=[], qualifier=None, selectors=[], value=null), operator=>>))",
      "line": 41
    },
    {
      "id": 10,
      "label": "If(BinaryOperation(operandl=Literal(postfix_operators=[], prefix_operators=[], qualifier=None, selectors=[], value=false), operandr=Literal(postfix_operators=[], prefix_operators=[], qualifier=None, selectors=[], value=false), operator=&&))",
      "line": 43
    },
    {
      "id": 11,
      "label": "LocalVariableDeclaration(annotations=[], declarators=[VariableDeclarator(dimensions=[], initializer=Literal(postfix_operators=[], prefix_operators=[], qualifier=None, selectors=[], value=null), name=__cfwr_var84)], modifiers=set(), type=ReferenceType(arguments=None, dimensions=[], name=Character, sub_type=None))",
      "line": 44
    },
    {
      "id": 12,
      "label": "Catch(__cfwr_e9)",
      "line": null
    },
    {
      "id": 13,
      "label": "Break",
      "line": 57
    },
    {
      "id": 14,
      "label": "Update(MemberReference(member=__cfwr_i49, postfix_operators=['++'], prefix_operators=[], qualifier=, selectors=[]))",
      "line": 39
    },
    {
      "id": 15,
      "label": "Update(MemberReference(member=__cfwr_i64, postfix_operators=['++'], prefix_operators=[], qualifier=, selectors=[]))",
      "line": 38
    },
    {
      "id": 16,
      "label": "Catch(__cfwr_e82)",
      "line": null
    },
    {
      "id": 17,
      "label": "Return(Literal(postfix_operators=[], prefix_operators=[], qualifier=None, selectors=[], value=962))",
      "line": 59
    }
  ],
  "edges": [
    {
      "source": 0,
      "target": 2
    },
    {
      "source": 2,
      "target": 3
    },
    {
      "source": 2,
      "target": 4
    },
    {
      "source": 2,
      "target": 6
    },
    {
      "source": 2,
      "target": 10
    },
    {
      "source": 2,
      "target": 12
    },
    {
      "source": 2,
      "target": 16
    },
    {
      "source": 4,
      "target": 5
    },
    {
      "source": 5,
      "target": 2
    },
    {
      "source": 5,
      "target": 17
    },
    {
      "source": 6,
      "target": 7
    },
    {
      "source": 6,
      "target": 13
    },
    {
      "source": 7,
      "target": 8
    },
    {
      "source": 7,
      "target": 15
    },
    {
      "source": 8,
      "target": 9
    },
    {
      "source": 8,
      "target": 14
    },
    {
      "source": 9,
      "target": 2
    },
    {
      "source": 9,
      "target": 14
    },
    {
      "source": 10,
      "target": 11
    },
    {
      "source": 10,
      "target": 13
    },
    {
      "source": 11,
      "target": 13
    },
    {
      "source": 12,
      "target": 13
    },
    {
      "source": 14,
      "target": 7
    },
    {
      "source": 15,
      "target": 6
    },
    {
      "source": 16,
      "target": 13
    }
  ]
}